LICENSE
MANIFEST.in
README.md
setup.py
PyTimeMux8x8Acquisition/PyTMAcqGUI.py
PyTimeMux8x8Acquisition/TimeMuxGui.py
PyTimeMux8x8Acquisition/TimeMuxGui.ui
PyTimeMux8x8Acquisition/__init__.py
PyTimeMux8x8Acquisition.egg-info/PKG-INFO
PyTimeMux8x8Acquisition.egg-info/SOURCES.txt
PyTimeMux8x8Acquisition.egg-info/dependency_links.txt
PyTimeMux8x8Acquisition.egg-info/entry_points.txt
PyTimeMux8x8Acquisition.egg-info/requires.txt
PyTimeMux8x8Acquisition.egg-info/top_level.txt
PyTimeMux8x8Acquisition/PyTMCore/SampleGenerator.py
PyTimeMux8x8Acquisition/PyTMCore/TMacqCore.py
PyTimeMux8x8Acquisition/PyTMCore/TMacqThread.py
PyTimeMux8x8Acquisition/PyTMCore/__init__.py